[
    {
        "paikka": "El Chorro",
        "kuvaus": "The best",
        "arvio": 5
    },
    {
        "paikka": "Salmisaari",
        "kuvaus": "Kolme kerrosta",
        "arvio": 4
    },
    {
        "paikka": "Perro",
        "kuvaus": "Average",
        "arvio": 4
    },
    {
        "paikka": "ALOHA",
        "kuvaus": "Babe",
        "arvio": 2
    },
    {
        "paikka": "Keilaniemi",
        "kuvaus": "",
        "arvio": 0
    },
    {
        "paikka": "Lauttasaari",
        "kuvaus": "",
        "arvio": 0
    },
    {
        "paikka": "Kittilä",
        "kuvaus": "",
        "arvio": 0
    },
    {
        "paikka": "Kirkkonummi",
        "kuvaus": "Kivaa lähellä",
        "arvio": 2
    },
    {
        "paikka": "Kalasatama",
        "kuvaus": "Kiva kiva",
        "arvio": 2
    },
    {
        "paikka": "Puistola",
        "kuvaus": "Hyvät kalliot",
        "arvio": 5
    },
    {
        "paikka": "Kiiruna",
        "kuvaus": "",
        "arvio": 0
    },
    {
        "paikka": "Masala",
        "kuvaus": "",
        "arvio": 0
    },
    {
        "paikka": "Hervanta",
        "kuvaus": "",
        "arvio": 0
    },
    {
        "paikka": "Keilaniemi",
        "kuvaus": "Ei täällä voi kiipeillä",
        "arvio": 1
    },
    {
        "paikka": "Hirvensalmi",
        "kuvaus": "Voiko täälläkin kiivetä?",
        "arvio": 3
    }
]